streamlit/callbacks/__init__.py
streamlit/callbacks/base_connection.py
streamlit/callbacks/callbacks.py
streamlit/callbacks/inter_session.py
streamlit/callbacks/redis.py
streamlit/callbacks/websocket.py
streamlit_callbacks-0.0.5.dist-info/LICENSE
streamlit_callbacks-0.0.5.dist-info/METADATA
streamlit_callbacks-0.0.5.dist-info/WHEEL
streamlit_callbacks-0.0.5.dist-info/top_level.txt
streamlit_callbacks-0.0.5.dist-info/RECORD
