Metadata-Version: 2.1
Name: streamlit-callbacks
Version: 0.0.5
Summary: UNKNOWN
Home-page: https://github.com/FloWide/streamlit_callbacks
Author: 
Author-email: 
License: UNKNOWN
Platform: UNKNOWN
Requires-Python: >=3.6
Requires-Dist: streamlit (>=0.76.0)
